demo/__init__.py
demo/urls.py
demo/settings/__init__.py
demo/settings/dev.py
wagtail_rest_pack/__init__.py
wagtail_rest_pack/api/__init__.py
wagtail_rest_pack/api/endpoints.py
wagtail_rest_pack/breadcrumps/__init__.py
wagtail_rest_pack/breadcrumps/mixins.py
wagtail_rest_pack/breadcrumps/serializers.py
wagtail_rest_pack/comments/__init__.py
wagtail_rest_pack/comments/admin.py
wagtail_rest_pack/comments/apps.py
wagtail_rest_pack/comments/content_type.py
wagtail_rest_pack/comments/create.py
wagtail_rest_pack/comments/get.py
wagtail_rest_pack/comments/models.py
wagtail_rest_pack/comments/permission.py
wagtail_rest_pack/comments/update.py
wagtail_rest_pack/comments/urls.py
wagtail_rest_pack/comments/wagtail_hooks.py
wagtail_rest_pack/comments/migrations/0001_initial.py
wagtail_rest_pack/comments/migrations/0002_comment_updated_on.py
wagtail_rest_pack/comments/migrations/0003_comment_updated_by.py
wagtail_rest_pack/comments/migrations/0004_alter_comment_options.py
wagtail_rest_pack/comments/migrations/__init__.py
wagtail_rest_pack/custom_menu/__init__.py
wagtail_rest_pack/custom_menu/apps.py
wagtail_rest_pack/custom_menu/models.py
wagtail_rest_pack/custom_menu/serializers.py
wagtail_rest_pack/custom_menu/urls.py
wagtail_rest_pack/custom_menu/view.py
wagtail_rest_pack/custom_menu/migrations/0001_initial.py
wagtail_rest_pack/custom_menu/migrations/0002_alter_custommenu_name.py
wagtail_rest_pack/custom_menu/migrations/0003_auto_20211003_1538.py
wagtail_rest_pack/custom_menu/migrations/0004_custommenu_content.py
wagtail_rest_pack/custom_menu/migrations/0005_alter_custommenu_content.py
wagtail_rest_pack/custom_menu/migrations/0006_auto_20211003_1614.py
wagtail_rest_pack/custom_menu/migrations/0007_alter_custommenu_stream.py
wagtail_rest_pack/custom_menu/migrations/0008_alter_custommenu_stream.py
wagtail_rest_pack/custom_menu/migrations/0009_alter_custommenu_stream.py
wagtail_rest_pack/custom_menu/migrations/0010_auto_20221023_0845.py
wagtail_rest_pack-0.0.43.dist-info/LICENSE
wagtail_rest_pack-0.0.43.dist-info/METADATA
wagtail_rest_pack-0.0.43.dist-info/WHEEL
wagtail_rest_pack-0.0.43.dist-info/top_level.txt
wagtail_rest_pack-0.0.43.dist-info/RECORD
