Metadata-Version: 2.1
Name: wagtail-rest-pack
Version: 0.0.43
Summary: A small example package
Home-page: https://github.com/domibydzovsky/wagtail-rest-pack
Author: Dominik Bydzovsky
Author-email: dominikbydzovsky94@gmail.com
Project-URL: Bug Tracker, https://github.com/domibydzovsky/wagtail-rest-pack/issues
Classifier: Programming Language :: Python :: 3
Classifier: License :: OSI Approved :: MIT License
Classifier: Operating System :: OS Independent
Requires-Python: >=3.8
License-File: LICENSE
Requires-Dist: django (>3.0)
Requires-Dist: wagtail (>=4)
Requires-Dist: drf-extensions (>=0.6.0)
Requires-Dist: djangorestframework (>3.10.0)
